examples/__init__.py
examples/flask_demo.py
flask_look_mysql/__init__.py
flask_look_mysql/templates/index.html
tests/__init__.py
Flask_Look_Mysql-1.0.6.dist-info/LICENSE.txt
Flask_Look_Mysql-1.0.6.dist-info/METADATA
Flask_Look_Mysql-1.0.6.dist-info/WHEEL
Flask_Look_Mysql-1.0.6.dist-info/top_level.txt
Flask_Look_Mysql-1.0.6.dist-info/RECORD
