Metadata-Version: 2.1
Name: Flask-Look-Mysql
Version: 1.0.6
Summary: a look mysql html
Home-page: https://github.com/libaibuaidufu/Flask-Look-Mysql
Author: libaibuaidufu
Author-email: libaibuaidufu@gmail.com
License: MIT License
Keywords: flask look mysql html
Platform: any
Requires-Dist: flask
Requires-Dist: pymysql
Requires-Dist: cachelib
